[
  {
    "icon": "Bold",
    "name": "宛安小站",
    "link": "https://w45sen.top/"
  },
  {
    "icon": "File",
    "name": "文件服务",
    "link": "https://w.w45sen.top/"
  },
  {
    "icon": "Camera",
    "name": "家庭相册",
    "link": "https://p.w45sen.top/"
  },
  {
    "icon": "Film",
    "name": "影视资源",
    "link": "https://x.w45sen.top/"
  },
  {
    "icon": "Book",
    "name": "笔记服务",
    "link": "https://b.w45sen.top/"
  },
  {
    "icon": "Clipboard",
    "name": "随笔",
    "link": "https://m.w45sen.top/"
  },
  {
    "icon": "Sitemap",
    "name": "备用线路",
    "link": "http://bbb.w45sen.top/"
  },
  {
    "icon": "File",
    "name": "文件服务(快速)",
    "link": "https://ww.w45sen.top/"
  },
  {
    "icon": "Camera",
    "name": "家庭相册(快速)",
    "link": "https://ppp.w45sen.top/"
  },
  {
    "icon": "Images",
    "name": "宛安图床",
    "link": "https://e.w45sen.top/"
  }
]
